publiccomps/__init__.py
publiccomps-0.0.1.dist-info/licenses/LICENSE
publiccomps-0.0.1.dist-info/METADATA
publiccomps-0.0.1.dist-info/WHEEL
publiccomps-0.0.1.dist-info/top_level.txt
publiccomps-0.0.1.dist-info/RECORD
