Metadata-Version: 2.4
Name: publiccomps
Version: 0.0.1
Summary: Official SDK for accessing Public Comps data
Home-page: https://publiccomps.com
Author: Jon Ma
Author-email: jon@publiccomps.com
Classifier: Programming Language :: Python :: 3
Classifier: License :: OSI Approved :: MIT License
Classifier: Operating System :: OS Independent
Requires-Python: >=3.7
License-File: LICENSE
Dynamic: author
Dynamic: author-email
Dynamic: classifier
Dynamic: description
Dynamic: description-content-type
Dynamic: home-page
Dynamic: license-file
Dynamic: requires-python
Dynamic: summary
